Regressionizer/Regressionizer.py
Regressionizer/__init__.py
Regressionizer-0.1.9.dist-info/LICENSE
Regressionizer-0.1.9.dist-info/METADATA
Regressionizer-0.1.9.dist-info/WHEEL
Regressionizer-0.1.9.dist-info/top_level.txt
Regressionizer-0.1.9.dist-info/RECORD
