Metadata-Version: 2.1
Name: Regressionizer
Version: 0.1.9
Summary: Regression workflows package based on Least Squares Regression and Quantile Regression.
Home-page: https://github.com/antononcube/Python-Regressionizer
Author: Anton Antonov
Author-email: antononcube@posteo.net
Keywords: regression,quantile,quantile regression,linear,linear regression,workflow
Classifier: Programming Language :: Python :: 3
Classifier: License :: OSI Approved :: GNU General Public License v3 (GPLv3)
Classifier: Operating System :: OS Independent
Requires-Python: >=3.7
License-File: LICENSE
Requires-Dist: numpy
Requires-Dist: scipy
Requires-Dist: pandas
Requires-Dist: plotly
Requires-Dist: datetime
Requires-Dist: QuantileRegression>=0.1.5
Requires-Dist: OutlierIdentifiers>=0.1.2
